{
  "experiment_id": "1479505645458067538",
  "timestamp": "2026-04-03T01:54:00Z",
  "image_metadata": {
    "width": 480,
    "height": 300,
    "format": "JPG"
  },
  "ground_truth_objects": [
    {
      "label": "object 1",
      "abs_box_2d": [
        133,
        27,
        200,
        119
      ],
      "box_2d": [
        443,
        56,
        666,
        247
      ]
    },
    {
      "label": "object 1",
      "abs_box_2d": [
        145,
        141,
        154,
        154
      ],
      "box_2d": [
        483,
        293,
        513,
        320
      ]
    },
    {
      "label": "object 1",
      "abs_box_2d": [
        144,
        153,
        152,
        161
      ],
      "box_2d": [
        480,
        318,
        506,
        335
      ]
    },
    {
      "label": "object 1",
      "abs_box_2d": [
        144,
        159,
        155,
        173
      ],
      "box_2d": [
        480,
        331,
        516,
        360
      ]
    },
    {
      "label": "object 1",
      "abs_box_2d": [
        141,
        196,
        154,
        210
      ],
      "box_2d": [
        470,
        408,
        513,
        437
      ]
    },
    {
      "label": "object 1",
      "abs_box_2d": [
        144,
        222,
        155,
        236
      ],
      "box_2d": [
        480,
        462,
        516,
        491
      ]
    },
    {
      "label": "object 1",
      "abs_box_2d": [
        145,
        237,
        154,
        248
      ],
      "box_2d": [
        483,
        493,
        513,
        516
      ]
    },
    {
      "label": "object 1",
      "abs_box_2d": [
        145,
        252,
        156,
        266
      ],
      "box_2d": [
        483,
        525,
        520,
        554
      ]
    },
    {
      "label": "object 1",
      "abs_box_2d": [
        144,
        266,
        160,
        287
      ],
      "box_2d": [
        480,
        554,
        533,
        597
      ]
    },
    {
      "label": "object 1",
      "abs_box_2d": [
        142,
        304,
        167,
        337
      ],
      "box_2d": [
        473,
        633,
        556,
        702
      ]
    },
    {
      "label": "object 1",
      "abs_box_2d": [
        145,
        323,
        171,
        369
      ],
      "box_2d": [
        483,
        672,
        570,
        768
      ]
    },
    {
      "label": "object 1",
      "abs_box_2d": [
        141,
        399,
        160,
        425
      ],
      "box_2d": [
        470,
        831,
        533,
        885
      ]
    }
  ]
}